simplebot_poi.py
simplebot_poi-1.0.0.dist-info/LICENSE
simplebot_poi-1.0.0.dist-info/METADATA
simplebot_poi-1.0.0.dist-info/WHEEL
simplebot_poi-1.0.0.dist-info/entry_points.txt
simplebot_poi-1.0.0.dist-info/top_level.txt
simplebot_poi-1.0.0.dist-info/RECORD
